setup.py
strudel/Fields.py
strudel/Parser.py
strudel/__init__.py
strudel/_version.py
strudel/vobj.py
strudel.egg-info/PKG-INFO
strudel.egg-info/SOURCES.txt
strudel.egg-info/dependency_links.txt
strudel.egg-info/top_level.txt