Metadata-Version: 1.1
Name: strudel
Version: 0.1.0
Summary: A Python 3 Vcard parser.
Home-page: http://github.com/concordusapps/strudel
Author: Concordus Applications
Author-email: support@concordusapps.com
License: UNKNOWN
Platform: UNKNOWN
Classifier: Development Status :: 3 - Alpha
Classifier: Intended Audience :: Developers
Classifier: Intended Audience :: System Administrators
Classifier: License :: OSI Approved :: MIT License
Classifier: Operating System :: OS Independent
Classifier: Programming Language :: Python :: 3.3
Classifier: Topic :: Software Development :: Libraries :: Python Modules
Classifier: Topic :: Utilities
